Metadata-Version: 2.1
Name: regressionabz11
Version: 1.0.0
Summary: An awesome package that does something
Home-page: http://pypi.python.org/pypi/regressionabz11/
Author: Moncef
Author-email: m.anani@esi-sba.dz
License: LICENSE.txt
License-File: LICENSE.txt
